mkdocs_ezlinks_plugin/__init__.py
mkdocs_ezlinks_plugin/file_mapper.py
mkdocs_ezlinks_plugin/plugin.py
mkdocs_ezlinks_plugin/replacer.py
mkdocs_ezlinks_plugin/types.py
mkdocs_ezlinks_plugin/scanners/__init__.py
mkdocs_ezlinks_plugin/scanners/base_link_scanner.py
mkdocs_ezlinks_plugin/scanners/md_link_scanner.py
mkdocs_ezlinks_plugin/scanners/reference_link_scanner.py
mkdocs_ezlinks_plugin/scanners/wiki_link_scanner.py
mkdocs_ezlinked_plugin-0.3.3.dist-info/LICENSE
mkdocs_ezlinked_plugin-0.3.3.dist-info/METADATA
mkdocs_ezlinked_plugin-0.3.3.dist-info/WHEEL
mkdocs_ezlinked_plugin-0.3.3.dist-info/entry_points.txt
mkdocs_ezlinked_plugin-0.3.3.dist-info/top_level.txt
mkdocs_ezlinked_plugin-0.3.3.dist-info/RECORD
