Metadata-Version: 2.1
Name: mkdocs-ezlinked-plugin
Version: 0.3.3
Summary: A mkdocs plugin that makes linking to other documents easy.
Home-page: https://github.com/Mara-Li/mkdocs-ezlinks-plugin
Author: Mara-Li
Author-email: Mara-Li@outlook.fr
License: MIT
Keywords: mkdocs,wikilinks,ezlinks,obsidian,roam
Classifier: Development Status :: 3 - Alpha
Classifier: Intended Audience :: Developers
Classifier: Intended Audience :: Information Technology
Classifier: Programming Language :: Python
Classifier: Programming Language :: Python :: 3 :: Only
Requires-Python: >=3.6
License-File: LICENSE
Requires-Dist: mkdocs
Requires-Dist: pygtrie (==2.*)
Requires-Dist: dataclasses (>=0.7) ; python_version < "3.7.0"
